Metadata-Version: 1.1
Name: couchquery
Version: 0.10.0
Summary: Python library for simple and dynamic access to CouchDB
Home-page: http://nicolaisi.github.io/couchquery/
Author: Mikeal Rogers
Author-email: mikeal.rogers@gmail.com
License: MPL 1.1/GPL 2.0/LGPL 2.1
Platform: Any
Classifier: Development Status :: 4 - Beta
Classifier: Environment :: Console
Classifier: Intended Audience :: Developers
Classifier: License :: OSI Approved :: Mozilla Public License 1.1 (MPL 1.1)
Classifier: Operating System :: OS Independent
Classifier: Topic :: Software Development :: Libraries :: Python Modules
